rapport-0.1.4.data/scripts/rapport
rapport/template.py
rapport/util.py
rapport/plugin.py
rapport/email.py
rapport/report.py
rapport/config.py
rapport/setup.py
rapport/timeframe.py
rapport/cli.py
rapport/__init__.py
rapport/config/rapport.conf
rapport/templates/email/subject.text.jinja2
rapport/templates/email/body.text.jinja2
rapport/templates/web/index.html.jinja2
rapport/templates/plugin/twitter.text.jinja2
rapport/templates/plugin/trello.text.jinja2
rapport/templates/plugin/mediawiki.text.jinja2
rapport/templates/plugin/github.text.jinja2
rapport/templates/plugin/bugzilla.text.jinja2
rapport/templates/plugin/gerrit.html.jinja2
rapport/templates/plugin/gerrit.text.jinja2
rapport/plugins/bugzilla.py
rapport/plugins/github.py
rapport/plugins/mediawiki.py
rapport/plugins/openbuildservice.py
rapport/plugins/twitter.py
rapport/plugins/trello.py
rapport/plugins/gerrit.py
rapport/plugins/__init__.py
rapport-0.1.4.dist-info/WHEEL
rapport-0.1.4.dist-info/RECORD
rapport-0.1.4.dist-info/pydist.json
rapport-0.1.4.dist-info/top_level.txt
rapport-0.1.4.dist-info/METADATA
rapport-0.1.4.dist-info/DESCRIPTION.rst
