Metadata-Version: 2.0
Name: rapport
Version: 0.1.4
Summary: Work report generator for the lazy
Home-page: http://github.com/saschpe/rapport
Author: Sascha Peilicke
Author-email: saschpe@gmx.de
License: Apache-2.0
Platform: UNKNOWN
Classifier: Development Status :: 4 - Beta
Classifier: Environment :: Console
Classifier: Intended Audience :: End Users/Desktop
Classifier: Intended Audience :: Developers
Classifier: Intended Audience :: System Administrators
Classifier: License :: OSI Approved :: Apache Software License
Classifier: Operating System :: MacOS :: MacOS X
Classifier: Operating System :: POSIX
Classifier: Programming Language :: Python
Classifier: Programming Language :: Python :: 2.6
Classifier: Programming Language :: Python :: 2.7
Requires-Dist: argparse
Requires-Dist: futures
Requires-Dist: httplib2
Requires-Dist: lxml
Requires-Dist: Jinja2
Requires-Dist: paramiko
Requires-Dist: python-bugzilla
Requires-Dist: requests
Requires-Dist: trolly
Requires-Dist: tweepy
